MANIFEST.in
setup.py
Tribus.egg-info/PKG-INFO
Tribus.egg-info/SOURCES.txt
Tribus.egg-info/dependency_links.txt
Tribus.egg-info/entry_points.txt
Tribus.egg-info/not-zip-safe
Tribus.egg-info/requires.txt
Tribus.egg-info/top_level.txt
tribus/__init__.py
tribus/main.py
tribus/cli/__init__.py
tribus/cli/commands.py
tribus/cli/helpers/__init__.py
tribus/cli/helpers/image.py
tribus/cli/helpers/package.py
tribus/cli/helpers/source.py
tribus/common/__init__.py
tribus/common/commands.py
tribus/common/dictconfig.py
tribus/common/logger.py
tribus/common/recorder.py
tribus/common/repository.py
tribus/common/utils.py
tribus/common/validators.py
tribus/common/version.py
tribus/common/fabric/__init__.py
tribus/common/fabric/local.py
tribus/common/setup/__init__.py
tribus/common/setup/build.py
tribus/common/setup/clean.py
tribus/common/setup/install.py
tribus/common/setup/maint.py
tribus/common/setup/message_extractors.py
tribus/common/setup/utils.py
tribus/config/__init__.py
tribus/config/base.py
tribus/config/brand.py
tribus/config/gtk.py
tribus/config/ldap.py
tribus/config/logger.py
tribus/config/pkg.py
tribus/config/pkgrecorder.py
tribus/config/sphinx.py
tribus/config/web.py
tribus/config/data/debian-build-dependencies.list
tribus/config/data/debian-maint-dependencies.list
tribus/config/data/debian-run-dependencies.list
tribus/config/data/dists-template
tribus/config/data/exclude-packages.list
tribus/config/data/exclude-patterns.list
tribus/config/data/exclude-sources.list
tribus/config/data/include-data-patterns.list
tribus/config/data/preseed-db.sql
tribus/config/data/preseed-ldap-users.ldif
tribus/config/data/preseed-slapd-debconf.conf
tribus/config/data/python-classifiers.list
tribus/config/data/python-dependencies.list
tribus/config/data/tribus.nginx.conf
tribus/config/data/tribus.nginx.conf.in
tribus/config/data/tribus.uwsgi.ini
tribus/config/data/tribus.uwsgi.ini.in
tribus/data/__init__.py
tribus/data/docs/man/tribus.rst
tribus/data/docs/rst/authors.rst
tribus/data/docs/rst/conf.py
tribus/data/docs/rst/contributors.rst
tribus/data/docs/rst/copying.rst
tribus/data/docs/rst/faq.rst
tribus/data/docs/rst/index.rst
tribus/data/docs/rst/installation.rst
