Metadata-Version: 1.1
Name: Tribus
Version: 0.1.dev20131207073801
Summary: (u'Red social para la gesti\xf3n de comunidades de Software Libre.',)
Home-page: http://git.canaima.softwarelibre.gob.ve/?p=tribus.git;a=summary
Author: Desarrolladores de Tribus
Author-email: desarrolladores@canaima.softwarelibre.gob.ve
License: GPL
Keywords: Social Network,Continuous Integration,Source Code Management
Platform: Any
Classifier: Development Status :: 3 - Alpha
Classifier: Environment :: Web Environment
Classifier: Framework :: Django
Classifier: Intended Audience :: Developers
Classifier: License :: OSI Approved :: BSD License
Classifier: Operating System :: OS Independent
Classifier: Programming Language :: Python
Classifier: Programming Language :: Python :: 2
Classifier: Programming Language :: Python :: 2.7
Classifier: Programming Language :: Python :: 3
Classifier: Programming Language :: Python :: 3.2
Classifier: Programming Language :: Python :: 3.3
Classifier: Topic :: Internet :: WWW/HTTP
Classifier: Topic :: Internet :: WWW/HTTP :: Dynamic Content
Classifier: Topic :: Internet :: WWW/HTTP :: WSGI
Classifier: Topic :: Software Development :: Libraries :: Application Frameworks
Classifier: Topic :: Software Development :: Libraries :: Python Modules
